{
  "project_info": {
    "project_number": "121729574695",
    "firebase_url": "https://my-new-project-ccb8f.firebaseio.com",
    "project_id": "my-new-project-ccb8f",
    "storage_bucket": "my-new-project-ccb8f.appspot.com"
  },
  "client": [
    {
      "client_info": {
        "mobilesdk_app_id": "1:121729574695:android:b0034fa133795a9d",
        "android_client_info": {
          "package_name": "com.adityadua.myfcmproject28mproject"
        }
      },
      "oauth_client": [
        {
          "client_id": "121729574695-2v3namotps3hljpt14ss6ni28en0ov44.apps.googleusercontent.com",
          "client_type": 1,
          "android_info": {
            "package_name": "com.adityadua.myfcmproject28mproject",
            "certificate_hash": "938713a868f598abcc14ac3bfd728de2eb951d86"
          }
        },
        {
          "client_id": "121729574695-d0f13jrt311r341mu0shn7sb0buokuid.apps.googleusercontent.com",
          "client_type": 3
        }
      ],
      "api_key": [
        {
          "current_key": "AIzaSyBb7n3S7JnOOBdwGC27KNV0nSsKvT9NDRg"
        }
      ],
      "services": {
        "analytics_service": {
          "status": 1
        },
        "appinvite_service": {
          "status": 2,
          "other_platform_oauth_client": [
            {
              "client_id": "121729574695-d0f13jrt311r341mu0shn7sb0buokuid.apps.googleusercontent.com",
              "client_type": 3
            }
          ]
        },
        "ads_service": {
          "status": 2
        }
      }
    }
  ],
  "configuration_version": "1"
}